LICENSE.txt
MANIFEST.in
README.rst
setup.cfg
setup.py
tests/__init__.py
tests/test_exceptions.py
tests/test_resources.py
tests/test_ui_theme.py
tests/test_widgets.py
tests/testapi.py
tw2/__init__.py
tw2.jqplugins.ui.egg-info/PKG-INFO
tw2.jqplugins.ui.egg-info/SOURCES.txt
tw2.jqplugins.ui.egg-info/dependency_links.txt
tw2.jqplugins.ui.egg-info/entry_points.txt
tw2.jqplugins.ui.egg-info/namespace_packages.txt
tw2.jqplugins.ui.egg-info/not-zip-safe
tw2.jqplugins.ui.egg-info/requires.txt
tw2.jqplugins.ui.egg-info/top_level.txt
tw2/jqplugins/__init__.py
tw2/jqplugins/ui/__init__.py
tw2/jqplugins/ui/base.py
tw2/jqplugins/ui/defaults.py
tw2/jqplugins/ui/samples.py
tw2/jqplugins/ui/widgets.py
tw2/jqplugins/ui/static/jquery/ui/1.8.1/css/smoothness/jquery-ui.css
tw2/jqplugins/ui/static/jquery/ui/1.8.1/css/smoothness/images/ui-anim_basic_16x16.gif
tw2/jqplugins/ui/static/jquery/ui/1.8.1/css/smoothness/images/ui-bg_flat_0_aaaaaa_40x100.png
tw2/jqplugins/ui/static/jquery/ui/1.8.1/css/smoothness/images/ui-bg_flat_75_ffffff_40x100.png
tw2/jqplugins/ui/static/jquery/ui/1.8.1/css/smoothness/images/ui-bg_glass_55_fbf9ee_1x400.png
tw2/jqplugins/ui/static/jquery/ui/1.8.1/css/smoothness/images/ui-bg_glass_65_ffffff_1x400.png
tw2/jqplugins/ui/static/jquery/ui/1.8.1/css/smoothness/images/ui-bg_glass_75_dadada_1x400.png
tw2/jqplugins/ui/static/jquery/ui/1.8.1/css/smoothness/images/ui-bg_glass_75_e6e6e6_1x400.png
tw2/jqplugins/ui/static/jquery/ui/1.8.1/css/smoothness/images/ui-bg_glass_95_fef1ec_1x400.png
tw2/jqplugins/ui/static/jquery/ui/1.8.1/css/smoothness/images/ui-bg_highlight-soft_75_cccccc_1x100.png
tw2/jqplugins/ui/static/jquery/ui/1.8.1/css/smoothness/images/ui-icons_222222_256x240.png
tw2/jqplugins/ui/static/jquery/ui/1.8.1/css/smoothness/images/ui-icons_2e83ff_256x240.png
tw2/jqplugins/ui/static/jquery/ui/1.8.1/css/smoothness/images/ui-icons_454545_256x240.png
tw2/jqplugins/ui/static/jquery/ui/1.8.1/css/smoothness/images/ui-icons_888888_256x240.png
tw2/jqplugins/ui/static/jquery/ui/1.8.1/css/smoothness/images/ui-icons_cd0a0a_256x240.png
tw2/jqplugins/ui/static/jquery/ui/1.8.1/js/jquery-ui.js
tw2/jqplugins/ui/static/jquery/ui/1.8.1/js/jquery-ui.min.js
tw2/jqplugins/ui/static/jquery/ui/1.8.16/css/jquery-ui.css
tw2/jqplugins/ui/static/jquery/ui/1.8.16/css/jquery-ui.css.1
