Metadata-Version: 1.1
Name: tw2.jqplugins.ui
Version: 2.3.0
Summary: toscawidgets2 wrapper for jquery-ui
Home-page: http://github.com/toscawidgets/tw2.jqplugins.ui
Author: Ralph Bean
Author-email: rbean@redhat.com
License: MIT
Keywords: toscawidgets.widgets
Platform: UNKNOWN
Classifier: Development Status :: 5 - Production/Stable
Classifier: Environment :: Web Environment
Classifier: Environment :: Web Environment :: ToscaWidgets
Classifier: Topic :: Software Development :: Libraries :: Python Modules
Classifier: Topic :: Software Development :: Widget Sets
Classifier: Intended Audience :: Developers
Classifier: Operating System :: OS Independent
Classifier: Programming Language :: Python
Classifier: Programming Language :: JavaScript
Classifier: License :: OSI Approved :: MIT License
